simple_poetry/__init__.py
simple_poetry-0.1.0.dist-info/entry_points.txt
simple_poetry-0.1.0.dist-info/LICENSE
simple_poetry-0.1.0.dist-info/WHEEL
simple_poetry-0.1.0.dist-info/METADATA
simple_poetry-0.1.0.dist-info/RECORD
