Metadata-Version: 2.1
Name: simple-poetry
Version: 0.1.0
Summary: A clean, automated setup for publishing simple Python packages to PyPI and Anaconda.
Home-page: https://github.com/ppeetteerrs/simple-poetry
License: MIT
Author: Peter Yuen
Author-email: ppeetteerrsx@gmail.com
Requires-Python: >=3.8,<4.0
Classifier: License :: OSI Approved :: MIT License
Classifier: Programming Language :: Python :: 3
Classifier: Programming Language :: Python :: 3.10
Classifier: Programming Language :: Python :: 3.8
Classifier: Programming Language :: Python :: 3.9
Project-URL: Documentation, https://ppeetteerrs.github.io/simple-poetry
Project-URL: Repository, https://github.com/ppeetteerrs/simple-poetry
